flask_login/__about__.py
flask_login/__init__.py
flask_login/config.py
flask_login/login_manager.py
flask_login/mixins.py
flask_login/signals.py
flask_login/test_client.py
flask_login/utils.py
Flask_Login-0.6.2.dist-info/LICENSE
Flask_Login-0.6.2.dist-info/METADATA
Flask_Login-0.6.2.dist-info/WHEEL
Flask_Login-0.6.2.dist-info/top_level.txt
Flask_Login-0.6.2.dist-info/RECORD
