Metadata-Version: 2.1
Name: Flask-Login
Version: 0.6.2
Summary: User authentication and session management for Flask.
Home-page: https://github.com/maxcountryman/flask-login
Author: Matthew Frazier
Author-email: leafstormrush@gmail.com
Maintainer: Max Countryman
License: MIT
Project-URL: Documentation, https://flask-login.readthedocs.io/
Project-URL: Changes, https://github.com/maxcountryman/flask-login/blob/main/CHANGES.md
Project-URL: Source Code, https://github.com/maxcountryman/flask-login
Project-URL: Issue Tracker, https://github.com/maxcountryman/flask-login/issues
Classifier: Development Status :: 4 - Beta
Classifier: Environment :: Web Environment
Classifier: Framework :: Flask
Classifier: Intended Audience :: Developers
Classifier: License :: OSI Approved :: MIT License
Classifier: Operating System :: OS Independent
Classifier: Programming Language :: Python
Classifier: Topic :: Internet :: WWW/HTTP :: Dynamic Content
Classifier: Topic :: Software Development :: Libraries :: Python Modules
Requires-Python: >=3.7
License-File: LICENSE
